metabotk/__init__.py
metabotk/_version.py
metabotk/cli.py
metabotk/dataset_io.py
metabotk/dataset_operations.py
metabotk/dimensionality_reduction.py
metabotk/feature_selection.py
metabotk/imputation.py
metabotk/main.py
metabotk/metabolomic_dataset.py
metabotk/missing_handler.py
metabotk/models_handler.py
metabotk/normalization.py
metabotk/outliers_handler.py
metabotk/parse_and_setup.py
metabotk/py.typed
metabotk/scaling.py
metabotk/statistics_handler.py
metabotk/test.py
metabotk/utils.py
metabotk/visualization_handler.py
metabotk/old/interface.py
metabotk/old/providers_handler.py
metabotk-0.3.3.dist-info/METADATA
metabotk-0.3.3.dist-info/WHEEL
metabotk-0.3.3.dist-info/RECORD
