Metadata-Version: 2.4
Name: metabotk
Version: 0.3.3
Summary: MetabolomicsToolKit (metabotk) is a Python library for working with metabolomics data. It provides a variety of tools and methods for importing, exploring, manipulating and analyzing metabolomics data.
Requires-Python: >=3.12
Requires-Dist: boruta-py-versioned>=0.1.0
Requires-Dist: coverage>=7.6.10
Requires-Dist: dill>=0.3.9
Requires-Dist: miceforest>=6.0.3
Requires-Dist: numpy>=2.2.0
Requires-Dist: openpyxl>=3.1.5
Requires-Dist: pandas>=2.2.3
Requires-Dist: pyserrf>=0.2.1
Requires-Dist: pytest>=8.3.4
Requires-Dist: scikit-learn>=1.6.0
Requires-Dist: seaborn>=0.13.2
Requires-Dist: skloess>=0.1.3
Requires-Dist: statsmodels>=0.14.4
